ybankinplay/__init__.py
ybankinplay/base.py
ybankinplay/headless.py
ybankinplay/misc.py
ybankinplay/research.py
ybankinplay/screener.py
ybankinplay/ticker.py
ybankinplay/utils/__init__.py
ybankinplay/utils/countries.py
ybankinplay/utils/headers.py
ybankinplay/utils/impersonates.py
ybankinplay/utils/screeners.py
ybankinplay-2.3.8.6.dist-info/LICENSE.txt
ybankinplay-2.3.8.6.dist-info/METADATA
ybankinplay-2.3.8.6.dist-info/WHEEL
ybankinplay-2.3.8.6.dist-info/RECORD
