Metadata-Version: 2.3
Name: ybankinplay
Version: 2.3.8.6
Summary: Python wrapper for an unofficial Yahoo Finance API
License: MIT
Keywords: python,API,finance,stocks,Yahoo Finance
Author: Javier Irisarri
Author-email: jirisarri@bankinplay.com
Requires-Python: >=3.9.0,<4.0
Classifier: License :: OSI Approved :: MIT License
Classifier: Programming Language :: Python :: 3
Classifier: Programming Language :: Python :: 3.9
Classifier: Programming Language :: Python :: 3.10
Classifier: Programming Language :: Python :: 3.11
Classifier: Programming Language :: Python :: 3.12
Classifier: Programming Language :: Python :: 3.13
Provides-Extra: premium
Requires-Dist: beautifulsoup4 (>=4.13.4,<5.0.0)
Requires-Dist: curl_cffi (>=0.10,<0.11)
Requires-Dist: lxml (>=5.4.0,<6.0.0)
Requires-Dist: pandas (>=2.2.3,<3.0.0)
Requires-Dist: requests (>=2.32.3,<3.0.0)
Requires-Dist: requests-futures (>=1.0.2,<2.0.0)
Requires-Dist: selenium (>=4.32.0,<5.0.0) ; extra == "premium"
Requires-Dist: tqdm (>=4.65.0,<5.0.0)
Project-URL: Documentation, https://yahooquery.dpguthrie.com
